onegov.quill-0.5.0-py3.6-nspkg.pth
onegov/quill/.gitignore
onegov/quill/__init__.py
onegov/quill/fields.py
onegov/quill/integration.py
onegov/quill/upgrade.py
onegov/quill/validators.py
onegov/quill/widgets.py
onegov/quill/assets/css/custom.css
onegov/quill/assets/css/quill.placeholder.css
onegov/quill/assets/css/quill.snow.css
onegov/quill/assets/js/quill.js
onegov/quill/assets/js/quill.placeholder.js
onegov/quill/tests/conftest.py
onegov/quill/tests/test_fields.py
onegov/quill/tests/test_integration.py
onegov/quill/tests/test_validators.py
onegov/quill/tests/test_widgets.py
onegov.quill-0.5.0.dist-info/METADATA
onegov.quill-0.5.0.dist-info/WHEEL
onegov.quill-0.5.0.dist-info/entry_points.txt
onegov.quill-0.5.0.dist-info/namespace_packages.txt
onegov.quill-0.5.0.dist-info/top_level.txt
onegov.quill-0.5.0.dist-info/RECORD
